LICENSE
MANIFEST.in
README.rst
setup.cfg
setup.py
pyimeji/__init__.py
pyimeji/api.py
pyimeji/cli.py
pyimeji/config.py
pyimeji/resource.py
pyimeji/util.py
pyimeji.egg-info/PKG-INFO
pyimeji.egg-info/SOURCES.txt
pyimeji.egg-info/dependency_links.txt
pyimeji.egg-info/entry_points.txt
pyimeji.egg-info/not-zip-safe
pyimeji.egg-info/requires.txt
pyimeji.egg-info/top_level.txt
pyimeji/tests/__init__.py
pyimeji/tests/live_test_usecases.py
pyimeji/tests/test.json
pyimeji/tests/test_api.py
pyimeji/tests/test_cli.py
pyimeji/tests/test_config.py
pyimeji/tests/test_util.py
pyimeji/tests/resources/album.json
pyimeji/tests/resources/collection.json
pyimeji/tests/resources/collections.json
pyimeji/tests/resources/item.json
pyimeji/tests/resources/item_template_collection.json
pyimeji/tests/resources/item_template_profile.json
pyimeji/tests/resources/profile.json