Metadata-Version: 1.1
Name: pyimeji
Version: 1.2.2
Summary: A python wrapper for the imeji API
Home-page: https://github.com/imeji-community/pyimeji
Author: Robert Forkel & Max Planck Digital Library (MPDL)
Author-email: support@imeji.org
License: Apache License
